trim_reads.py
trim_reads-0.0.7.dist-info/METADATA
trim_reads-0.0.7.dist-info/WHEEL
trim_reads-0.0.7.dist-info/licenses/LICENSE
trim_reads-0.0.7.dist-info/RECORD
