Metadata-Version: 2.1
Name: trim_reads
Version: 0.0.7
Summary: Trim sequencing reads
Project-URL: Homepage, https://github.com/ajgouhier/trim_reads
Author-email: Arthur Gouhier <ajgouhier@gmail.com>
License: MIT
License-File: LICENSE
Classifier: License :: OSI Approved :: MIT License
Classifier: Operating System :: OS Independent
Classifier: Programming Language :: Python :: 3
Requires-Python: >=3.8
